pbip_tools/__init__.py
pbip_tools/cli.py
pbip_tools/json_utils.py
pbip_tools/type_aliases.py
pbip_tools/clean/clean_JSON.py
pbip_tools/smudge/smudge_JSON.py
pbip_tools-0.3.0.dist-info/METADATA
pbip_tools-0.3.0.dist-info/WHEEL
pbip_tools-0.3.0.dist-info/entry_points.txt
pbip_tools-0.3.0.dist-info/licenses/LICENSE
pbip_tools-0.3.0.dist-info/RECORD
