Metadata-Version: 2.4
Name: pbip-tools
Version: 0.3.0
Summary: Smudge and Clean filters for Power BI-generated JSON files.
Project-URL: Homepage, https://github.com/moshemoshe137/pbip-tools
Project-URL: Repository, https://github.com/moshemoshe137/pbip-tools
Project-URL: Issues, https://github.com/moshemoshe137/pbip-tools/issues
Author-email: Moshe Rubin <mosherubin137@gmail.com>
License: MIT License
License-File: LICENSE
Classifier: Development Status :: 2 - Pre-Alpha
Classifier: Intended Audience :: Developers
Classifier: Intended Audience :: Science/Research
Classifier: License :: OSI Approved :: MIT License
Classifier: Operating System :: OS Independent
Classifier: Programming Language :: Python :: 3.10
Classifier: Programming Language :: Python :: 3.11
Classifier: Programming Language :: Python :: 3.12
Classifier: Topic :: File Formats :: JSON
Classifier: Topic :: File Formats :: JSON :: JSON Schema
Classifier: Topic :: Software Development :: Version Control
Classifier: Topic :: Software Development :: Version Control :: Git
Requires-Python: >=3.10
